cutoml/__init__.py
cutoml/_version.py
cutoml/cutoml.py
cutoml/utils.py
cutoml-0.0.6.dist-info/LICENSE
cutoml-0.0.6.dist-info/METADATA
cutoml-0.0.6.dist-info/WHEEL
cutoml-0.0.6.dist-info/top_level.txt
cutoml-0.0.6.dist-info/RECORD
