Metadata-Version: 2.1
Name: cutoml
Version: 0.0.6
Summary: A lightweight automl framework
Home-page: https://github.com/omkarudawant/CutoML
Author: Omkar Udawant
Author-email: omkarudawant97@gmail.com
License: gpl-3.0
Download-URL: https://github.com/omkarudawant/CutoML/archive/0.0.6.tar.gz
Keywords: pipeline optimization,hyperparameter optimization,data science,machine learning
Platform: UNKNOWN
Classifier: Development Status :: 3 - Alpha
Classifier: Intended Audience :: Developers
Classifier: Topic :: Scientific/Engineering :: Artificial Intelligence
Classifier: License :: OSI Approved :: GNU Lesser General Public License v3 (LGPLv3)
Classifier: Programming Language :: Python :: 3
Requires-Python: >=3.6
Requires-Dist: scipy (>=1.5.1)
Requires-Dist: numpy (>=1.19.1)
Requires-Dist: scikit-learn (>=0.24.0)
Requires-Dist: pydantic
Requires-Dist: xgboost (>=1.3.1)
